pdc_auth/authenticator.py
pdc_auth/endpoint.py
pdc_auth/exceptions/authenticator_exc.py
pdc_auth/exceptions/base_exc.py
pdc_auth/exceptions/login_provider_exc.py
pdc_auth/login_provider.py
pdc_auth/models/config.py
pdc_auth-0.2.1.dist-info/WHEEL
pdc_auth-0.2.1.dist-info/METADATA
pdc_auth-0.2.1.dist-info/RECORD
