Metadata-Version: 2.1
Name: pdc-auth
Version: 0.2.1
Summary: pdc authentication manager
Author: hfrada
Author-email: madefrada@gmail.com
Requires-Python: >=3.10,<4.0
Classifier: Programming Language :: Python :: 3
Classifier: Programming Language :: Python :: 3.10
Requires-Dist: PyYAML (>=6.0,<7.0)
Requires-Dist: pydantic (>=1.10.2,<2.0.0)
Requires-Dist: requests (>=2.28.1,<3.0.0)
